retl/__init__.py
retl/retl.py
retl-0.0.2.dist-info/LICENSE
retl-0.0.2.dist-info/METADATA
retl-0.0.2.dist-info/WHEEL
retl-0.0.2.dist-info/top_level.txt
retl-0.0.2.dist-info/RECORD
