Metadata-Version: 2.1
Name: retl
Version: 0.0.2
Summary: A utility package in construction
Author-email: Berkay Avşar <berkay@goldshire.net>
Classifier: Programming Language :: Python :: 3
Classifier: License :: OSI Approved :: MIT License
Classifier: Operating System :: OS Independent
Requires-Python: >=3.7
License-File: LICENSE
